README.md
setup.py
allrecipes/__init__.py
python_allrecipes.egg-info/PKG-INFO
python_allrecipes.egg-info/SOURCES.txt
python_allrecipes.egg-info/dependency_links.txt
python_allrecipes.egg-info/not-zip-safe
python_allrecipes.egg-info/requires.txt
python_allrecipes.egg-info/top_level.txt