Metadata-Version: 1.0
Name: python-allrecipes
Version: 0.2.1
Summary: Easy-to-use Python API for the allrecipes.com cokking website.
Home-page: https://github.com/remaudcorentin-dev/python-allrecipes
Author: Corentin Remaud
Author-email: remaudcorentin.dev@gmail.com
License: MIT
Platform: UNKNOWN
